setup.py
list/main.py
listfiles.egg-info/PKG-INFO
listfiles.egg-info/SOURCES.txt
listfiles.egg-info/dependency_links.txt
listfiles.egg-info/top_level.txt