Metadata-Version: 1.0
Name: listfiles
Version: 1.0.0
Summary: A list file python project
Home-page: UNKNOWN
Author: dong jian
Author-email: UNKNOWN
License: MIT
Keywords: list file python
Platform: UNKNOWN
